LICENSE
MANIFEST.in
README.rst
setup.py
examples/__init__.py
examples/dynamic_requirements.py
examples/elasticsearch_index.py
examples/execution_summary_example.py
examples/foo.py
examples/foo_complex.py
examples/ftp_experiment_outputs.py
examples/hello_world.py
examples/kubernetes.py
examples/per_task_retry_policy.py
examples/pyspark_wc.py
examples/spark_als.py
examples/ssh_remote_execution.py
examples/terasort.py
examples/top_artists.py
examples/top_artists_spark.py
examples/wordcount.py
examples/wordcount_hadoop.py
luigi/__init__.py
luigi/__main__.py
luigi/__meta__.py
luigi/batch_notifier.py
luigi/cmdline.py
luigi/cmdline_parser.py
luigi/date_interval.py
luigi/db_task_history.py
luigi/event.py
luigi/execution_summary.py
luigi/format.py
luigi/freezing.py
luigi/interface.py
luigi/local_target.py
luigi/lock.py
luigi/metrics.py
luigi/mock.py
luigi/notifications.py
luigi/parameter.py
luigi/process.py
luigi/retcodes.py
luigi/rpc.py
luigi/scheduler.py
luigi/server.py
luigi/setup_logging.py
luigi/six.py
luigi/target.py
luigi/task.py
luigi/task_history.py
luigi/task_register.py
luigi/task_status.py
luigi/util.py
luigi/worker.py
luigi/configuration/__init__.py
luigi/configuration/base_parser.py
luigi/configuration/cfg_parser.py
luigi/configuration/core.py
luigi/configuration/toml_parser.py
luigi/contrib/__init__.py
luigi/contrib/azureblob.py
luigi/contrib/batch.py
luigi/contrib/beam_dataflow.py
luigi/contrib/bigquery.py
luigi/contrib/bigquery_avro.py
luigi/contrib/datadog_metric.py
luigi/contrib/dataproc.py
luigi/contrib/docker_runner.py
luigi/contrib/dropbox.py
luigi/contrib/ecs.py
luigi/contrib/esindex.py
luigi/contrib/external_daily_snapshot.py
luigi/contrib/external_program.py
luigi/contrib/ftp.py
luigi/contrib/gcp.py
luigi/contrib/gcs.py
luigi/contrib/hadoop.py
luigi/contrib/hadoop_jar.py
luigi/contrib/hive.py
luigi/contrib/kubernetes.py
luigi/contrib/lsf.py
luigi/contrib/lsf_runner.py
luigi/contrib/mongodb.py
luigi/contrib/mrrunner.py
luigi/contrib/mssqldb.py
luigi_k8s_jobs_runner.egg-info/PKG-INFO
luigi_k8s_jobs_runner.egg-info/SOURCES.txt
luigi_k8s_jobs_runner.egg-info/dependency_links.txt
luigi_k8s_jobs_runner.egg-info/entry_points.txt
luigi_k8s_jobs_runner.egg-info/requires.txt
luigi_k8s_jobs_runner.egg-info/top_level.txt
