Metadata-Version: 2.1
Name: luigi-k8s-jobs-runner
Version: 2.8.12.0b1
Summary: 
